nooscope_rpc/__init__.py
nooscope_rpc/api.py
nooscope_rpc/constants.py
nooscope_rpc/selfsigned.cert
nooscope_rpc-1.0.16.dist-info/LICENSE
nooscope_rpc-1.0.16.dist-info/METADATA
nooscope_rpc-1.0.16.dist-info/WHEEL
nooscope_rpc-1.0.16.dist-info/top_level.txt
nooscope_rpc-1.0.16.dist-info/RECORD
