Metadata-Version: 2.1
Name: nooscope-rpc
Version: 1.0.16
Summary: Simple TCP client impl to interact with IRC_BOT
Home-page: https://github.com/deacon-ralph/irc_bot
Author: HARDCHATTING_THUG
Author-email: cumdata@protonmail.com
License: UNKNOWN
Project-URL: Bug Tracker, https://github.com/deacon-ralph/irc_bot/issues
Platform: UNKNOWN
Classifier: Programming Language :: Python :: 3
Requires-Python: >=3.7
Requires-Dist: loguru >=0.5.3
